CODE_OF_CONDUCT.md
Contributing.md
MANIFEST
README.md
license.txt
setup.cfg
setup.py
__pycache__/Forecaster.cpython-37.pyc
__pycache__/Forecaster.cpython-38.pyc
__pycache__/Grids.cpython-37.pyc
__pycache__/Grids.cpython-38.pyc
assets/logo2.png
docs/0.17
docs/Makefile
docs/about.rst
docs/change_log.md
docs/conf.py
docs/index.rst
docs/initialization.rst
docs/installation.rst
docs/make.bat
docs/requirements.txt
docs/warnings.log
docs/Forecaster/AnomalyDetector.rst
docs/Forecaster/Forecaster.rst
docs/Forecaster/ForecasterGlobals.ipynb
docs/Forecaster/GridGenerator.rst
docs/Forecaster/MVForecaster.rst
docs/Forecaster/Multiseries.rst
docs/Forecaster/Notebook.rst
docs/Forecaster/SeriesTransformer.rst
docs/Forecaster/Util.rst
docs/Forecaster/_forecast.rst
docs/Forecaster/warnings.log
src/SCALECAST.egg-info/PKG-INFO
src/SCALECAST.egg-info/SOURCES.txt
src/SCALECAST.egg-info/dependency_links.txt
src/SCALECAST.egg-info/requires.txt
src/SCALECAST.egg-info/top_level.txt
src/scalecast/AnomalyDetector.py
src/scalecast/Forecaster.py
src/scalecast/GridGenerator.py
src/scalecast/MVForecaster.py
src/scalecast/SeriesTransformer.py
src/scalecast/__init__.py
src/scalecast/multiseries.py
src/scalecast/notebook.py
src/scalecast/util.py
src/scalecast/__pycache__/AnomalyDetector.cpython-38.pyc
src/scalecast/__pycache__/Forecaster.cpython-38.pyc
src/scalecast/__pycache__/GridGenerator.cpython-38.pyc
src/scalecast/__pycache__/Grids.cpython-38.pyc
src/scalecast/__pycache__/MVForecaster.cpython-38.pyc
src/scalecast/__pycache__/MVForecaster_dev_.cpython-38.pyc
src/scalecast/__pycache__/MVGrids.cpython-38.pyc
src/scalecast/__pycache__/SeriesTransformer.cpython-38.pyc
src/scalecast/__pycache__/__init__.cpython-38.pyc
src/scalecast/__pycache__/multiseries.cpython-38.pyc
src/scalecast/__pycache__/notebook.cpython-38.pyc
src/scalecast/__pycache__/results_vis_mv.cpython-38.pyc
src/scalecast/__pycache__/util.cpython-38.pyc