Metadata-Version: 2.1
Name: SCALECAST
Version: 0.12.2
Summary: The practitioner's time series forecasting library
Home-page: https://github.com/mikekeith52/scalecast
Author: Michael Keith
Author-email: mikekeith52@gmail.com
License: MIT
Project-URL: GitHub, https://github.com/mikekeith52/scalecast
Project-URL: Read the Docs, https://scalecast.readthedocs.io/en/latest/
Project-URL: Examples, https://scalecast-examples.readthedocs.io/en/latest/
Keywords: FORECAST,SCALE,DYNAMIC,MACHINE LEARNING,APPLIED
Platform: UNKNOWN
